{
    "overall":  "OK",
    "timestamp":  "2025-12-26T23:35:55",
    "firewall":  {
                     "found":  7,
                     "timestamp":  "2025-12-26T23:35:49",
                     "modified":  [

                                  ],
                     "expected":  7,
                     "missing":  [

                                 ],
                     "status":  "OK"
                 },
    "integrity":  {
                      "status":  "OK",
                      "timestamp":  "2025-12-26T23:35:55",
                      "missing":  [

                                  ],
                      "drift":  [

                                ]
                  },
    "registry":  {
                     "status":  "OK",
                     "timestamp":  "2025-12-26T23:35:53",
                     "missingKeys":  [

                                     ],
                     "drift":  [

                               ]
                 }
}
